see_rnn/__init__.py
see_rnn/_backend.py
see_rnn/inspect_gen.py
see_rnn/inspect_rnn.py
see_rnn/utils.py
see_rnn/visuals_gen.py
see_rnn/visuals_rnn.py
see_rnn-1.15.1.dist-info/LICENSE
see_rnn-1.15.1.dist-info/METADATA
see_rnn-1.15.1.dist-info/WHEEL
see_rnn-1.15.1.dist-info/top_level.txt
see_rnn-1.15.1.dist-info/zip-safe
see_rnn-1.15.1.dist-info/RECORD
