Metadata-Version: 2.1
Name: see-rnn
Version: 1.15.1
Summary: RNN and general weights, gradients, & activations visualization in Keras & TensorFlow
Home-page: https://github.com/OverLordGoldDragon/see-rnn
Author: OverLordGoldDragon
Author-email: 16495490+OverLordGoldDragon@users.noreply.github.com
License: MIT
Keywords: rnn tensorflow keras visualization deep-learning lstm gru
Platform: UNKNOWN
Classifier: Programming Language :: Python :: 3.6
Classifier: Programming Language :: Python :: 3.7
Classifier: License :: OSI Approved :: MIT License
Classifier: Operating System :: OS Independent
Classifier: Intended Audience :: Developers
Classifier: Intended Audience :: Education
Classifier: Intended Audience :: Information Technology
Classifier: Intended Audience :: Science/Research
Classifier: Topic :: Utilities
Classifier: Topic :: Scientific/Engineering
Classifier: Topic :: Scientific/Engineering :: Artificial Intelligence
Classifier: Topic :: Scientific/Engineering :: Information Analysis
Classifier: Topic :: Software Development
Classifier: Topic :: Software Development :: Libraries :: Python Modules
Requires-Dist: numpy
Requires-Dist: matplotlib
